graylogger/HTTPHandler.py
graylogger/__init__.py
graylogger-0.2.4.dist-info/LICENSE
graylogger-0.2.4.dist-info/METADATA
graylogger-0.2.4.dist-info/WHEEL
graylogger-0.2.4.dist-info/top_level.txt
graylogger-0.2.4.dist-info/RECORD
