Metadata-Version: 2.1
Name: graylogger
Version: 0.2.4
Summary: Набор graylog хэндлеров для библиотеки logging.
Home-page: https://github.com/Oficerov/Graylogging
Author: v.oficerov
Author-email: valeryoficerov@gmail.ru
License: MIT License
Download-URL: https://github.com/Oficerov/Graylogging/archive/refs/heads/v0.2.4.zip
Platform: UNKNOWN
Classifier: License :: OSI Approved :: MIT License
Classifier: Operating System :: OS Independent
Classifier: Intended Audience :: End Users/Desktop
Classifier: Intended Audience :: Developers
Classifier: Programming Language :: Python
Classifier: Programming Language :: Python :: 3.10
Classifier: Programming Language :: Python :: 3.11
Classifier: Programming Language :: Python :: Implementation :: PyPy
Classifier: Programming Language :: Python :: Implementation :: CPython
License-File: LICENSE
